{"10_Metropolis_(1927_film)": [{"kind": "query-pageimage", "file": "File:Metropolis1927-logo.svg", "orig": "Metropolis1927-logo.svg", "timestamp": "2015-01-07T07:39:33Z", "size": 3331, "width": 228, "height": 108, "url": "https://upload.wikimedia.org/wikipedia/commons/8/83/Metropolis1927-logo.svg", "descriptionurl": "https://commons.wikimedia.org/wiki/File:Metropolis1927-logo.svg", "descriptionshorturl": "https://commons.wikimedia.org/w/index.php?curid=37717604", "title": "File:Metropolis1927-logo.svg", "metadata": {"DateTime": {"value": "2015-01-07 07:39:33", "source": "mediawiki-metadata", "hidden": ""}, "ObjectName": {"value": "Metropolis1927-logo", "source": "mediawiki-metadata", "hidden": ""}, "CommonsMetadataExtension": {"value": 1.2, "source": "extension", "hidden": ""}, "Categories": {"value": "Metropolis (film)|PD textlogo|SVG movie logos|SVG text logos|With trademark", "source": "commons-categories", "hidden": ""}, "Assessments": {"value": "", "source": "commons-categories", "hidden": ""}, "ImageDescription": {"value": "<a href=\"https://de.wikipedia.org/wiki/Metropolis_(Film)\" class=\"extiw\" title=\"de:Metropolis (Film)\"><i>Metropolis</i></a> (1927) Logo", "source": "commons-desc-page"}, "DateTimeOriginal": {"value": "2011-05-05", "source": "commons-desc-page"}, "Credit": {"value": "<a rel=\"nofollow\" class=\"external free\" href=\"http://www.seeklogo.com/files/M/Metropolis-vector-logo-4AF59A3F79-seeklogo.com.zip\">http://www.seeklogo.com/files/M/Metropolis-vector-logo-4AF59A3F79-seeklogo.com.zip</a>", "source": "commons-desc-page", "hidden": ""}, "Artist": {"value": "metropolis / fritz lang", "source": "commons-desc-page"}, "LicenseShortName": {"value": "Public domain", "source": "commons-desc-page", "hidden": ""}, "UsageTerms": {"value": "Public domain", "source": "commons-desc-page", "hidden": ""}, "AttributionRequired": {"value": "false", "source": "commons-desc-page", "hidden": ""}, "Copyrighted": {"value": "False", "source": "commons-desc-page", "hidden": ""}, "Restrictions": {"value": "trademarked", "source": "commons-desc-page", "hidden": ""}, "License": {"value": "pd", "source": "commons-templates", "hidden": ""}}}, {"kind": "query-thumbnail", "width": 240, "height": 114, "url": "https://upload.wikimedia.org/wikipedia/commons/thumb/8/83/Metropolis1927-logo.svg/240px-Metropolis1927-logo.svg.png", "file": "File:Metropolis1927-logo.svg", "orig": "Metropolis1927-logo.svg"}, {"kind": "query-pageimage", "file": "File:Metropolis1927-logo.svg", "orig": "Metropolis1927-logo.svg", "timestamp": "2015-01-07T07:39:33Z", "size": 3331, "width": 228, "height": 108, "url": "https://upload.wikimedia.org/wikipedia/commons/8/83/Metropolis1927-logo.svg", "descriptionurl": "https://commons.wikimedia.org/wiki/File:Metropolis1927-logo.svg", "descriptionshorturl": "https://commons.wikimedia.org/w/index.php?curid=37717604", "title": "File:Metropolis1927-logo.svg", "metadata": {"DateTime": {"value": "2015-01-07 07:39:33", "source": "mediawiki-metadata", "hidden": ""}, "ObjectName": {"value": "Metropolis1927-logo", "source": "mediawiki-metadata", "hidden": ""}, "CommonsMetadataExtension": {"value": 1.2, "source": "extension", "hidden": ""}, "Categories": {"value": "Metropolis (film)|PD textlogo|SVG movie logos|SVG text logos|With trademark", "source": "commons-categories", "hidden": ""}, "Assessments": {"value": "", "source": "commons-categories", "hidden": ""}, "ImageDescription": {"value": "<a href=\"https://de.wikipedia.org/wiki/Metropolis_(Film)\" class=\"extiw\" title=\"de:Metropolis (Film)\"><i>Metropolis</i></a> (1927) Logo", "source": "commons-desc-page"}, "DateTimeOriginal": {"value": "2011-05-05", "source": "commons-desc-page"}, "Credit": {"value": "<a rel=\"nofollow\" class=\"external free\" href=\"http://www.seeklogo.com/files/M/Metropolis-vector-logo-4AF59A3F79-seeklogo.com.zip\">http://www.seeklogo.com/files/M/Metropolis-vector-logo-4AF59A3F79-seeklogo.com.zip</a>", "source": "commons-desc-page", "hidden": ""}, "Artist": {"value": "metropolis / fritz lang", "source": "commons-desc-page"}, "LicenseShortName": {"value": "Public domain", "source": "commons-desc-page", "hidden": ""}, "UsageTerms": {"value": "Public domain", "source": "commons-desc-page", "hidden": ""}, "AttributionRequired": {"value": "false", "source": "commons-desc-page", "hidden": ""}, "Copyrighted": {"value": "False", "source": "commons-desc-page", "hidden": ""}, "Restrictions": {"value": "trademarked", "source": "commons-desc-page", "hidden": ""}, "License": {"value": "pd", "source": "commons-templates", "hidden": ""}}}, {"kind": "query-thumbnail", "width": 240, "height": 114, "url": "https://upload.wikimedia.org/wikipedia/commons/thumb/8/83/Metropolis1927-logo.svg/240px-Metropolis1927-logo.svg.png", "file": "File:Metropolis1927-logo.svg", "orig": "Metropolis1927-logo.svg"}, {"kind": "parse-image", "file": "File:Metropolis (German three-sheet poster).jpg", "orig": "Metropolis (German three-sheet poster).jpg", "timestamp": "2020-03-11T22:46:51Z", "size": 75813, "width": 210, "height": 475, "url": "https://upload.wikimedia.org/wikipedia/en/9/97/Metropolis_%28German_three-sheet_poster%29.jpg", "descriptionurl": "https://en.wikipedia.org/wiki/File:Metropolis_(German_three-sheet_poster).jpg", "descriptionshorturl": "https://en.wikipedia.org/w/index.php?curid=63350586", "title": "File:Metropolis (German three-sheet poster).jpg", "metadata": {"DateTime": {"value": "2020-03-11 22:46:51", "source": "mediawiki-metadata", "hidden": ""}, "ObjectName": {"value": "Metropolis (German three-sheet poster)", "source": "mediawiki-metadata", "hidden": ""}, "CommonsMetadataExtension": {"value": 1.2, "source": "extension", "hidden": ""}, "Categories": {"value": "All non-free media|Noindexed pages|Non-free rationale as na|Out of copyright in 2040|Wikipedia files not suitable for Commons|Wikipedia non-free files for NFUR review", "source": "commons-categories", "hidden": ""}, "Assessments": {"value": "", "source": "commons-categories", "hidden": ""}, "ImageDescription": {"value": "Three-sheet poster for the 1927 German film <i><a href=\"//en.wikipedia.org/wiki/Metropolis_(1927_film)\" title=\"Metropolis (1927 film)\">Metropolis</a></i> depicting the <i>Maschinenmensch</i> (Machine-person) in front of the titular dystopian city of the future. This version of the poster accompanied its world premiere and domestic theatrical release in Germany. An international version of the same poster (which can be seen <a rel=\"nofollow\" class=\"external text\" href=\"https://www.moma.org/collection/works/88252\">at MoMA.org</a>) used the same illustration and design without the German-language credits.", "source": "commons-desc-page"}, "Artist": {"value": "Illustration by <a href=\"//en.wikipedia.org/wiki/Heinz_Schulz-Neudamm\" title=\"Heinz Schulz-Neudamm\">Heinz Schulz-Neudamm</a>. Distributed by <a href=\"//en.wikipedia.org/wiki/UFA_GmbH\" title=\"UFA GmbH\">UFA</a>.", "source": "commons-desc-page"}, "Credit": {"value": "<a rel=\"nofollow\" class=\"external text\" href=\"https://www.moma.org/collection/works/88251\">MoMA.org</a>", "source": "commons-desc-page", "hidden": ""}, "LicenseShortName": {"value": "Fair use", "source": "commons-desc-page", "hidden": ""}, "UsageTerms": {"value": "<a href=\"//en.wikipedia.org/wiki/Wikipedia:Non-free_use_rationale_guideline\" title=\"Wikipedia:Non-free use rationale guideline\">Fair use</a> of copyrighted material in the context of <a href=\"//en.wikipedia.org/wiki/Metropolis_(1927_film)\" title=\"Metropolis (1927 film)\">Metropolis (1927 film)</a>", "source": "commons-desc-page", "hidden": ""}, "LicenseUrl": {"value": "//en.wikipedia.org/wiki/File:Metropolis_(German_three-sheet_poster).jpg", "source": "commons-desc-page", "hidden": ""}, "NonFree": {"value": "true", "source": "commons-desc-page", "hidden": ""}, "Copyrighted": {"value": "True", "source": "commons-desc-page", "hidden": ""}, "Restrictions": {"value": "", "source": "commons-desc-page", "hidden": ""}}}, {"file": "File:Maria from the film Metropolis, on display at the Robot Hall of Fame.jpg", "kind": "wikidata-image", "orig": "Maria from the film Metropolis, on display at the Robot Hall of Fame.jpg", "timestamp": "2018-03-29T23:37:08Z", "size": 4236880, "width": 3168, "height": 4752, "url": "https://upload.wikimedia.org/wikipedia/commons/2/2d/Maria_from_the_film_Metropolis%2C_on_display_at_the_Robot_Hall_of_Fame.jpg", "descriptionurl": "https://commons.wikimedia.org/wiki/File:Maria_from_the_film_Metropolis,_on_display_at_the_Robot_Hall_of_Fame.jpg", "descriptionshorturl": "https://commons.wikimedia.org/w/index.php?curid=27508212", "title": "File:Maria from the film Metropolis, on display at the Robot Hall of Fame.jpg", "metadata": {"DateTime": {"value": "2018-03-29 23:37:08", "source": "mediawiki-metadata", "hidden": ""}, "ObjectName": {"value": "Maria from the film Metropolis, on display at the Robot Hall of Fame", "source": "mediawiki-metadata", "hidden": ""}, "CommonsMetadataExtension": {"value": 1.2, "source": "extension", "hidden": ""}, "Categories": {"value": "Flickr images reviewed by FlickreviewR|Maschinenmensch|Pages with maps|Replicas|Robot Hall of Fame|Statues of robots", "source": "commons-categories", "hidden": ""}, "Assessments": {"value": "", "source": "commons-categories", "hidden": ""}, "GPSLatitude": {"value": "40.445666", "source": "commons-desc-page"}, "GPSLongitude": {"value": "-80.018167", "source": "commons-desc-page"}, "GPSMapDatum": {"value": "WGS-84", "source": "commons-desc-page", "hidden": ""}, "ImageDescription": {"value": "Replica of the character Maria from <i>Metropolis</i>. This image is freely available under the <a rel=\"nofollow\" class=\"external text\" href=\"https://creativecommons.org/licenses/by-sa/3.0/us/legalcode\">Creative Commons Attribution-ShareAlike</a> license.", "source": "commons-desc-page"}, "DateTimeOriginal": {"value": "2011-03-08 15:07", "source": "commons-desc-page"}, "Credit": {"value": "<a rel=\"nofollow\" class=\"external text\" href=\"https://www.flickr.com/photos/jiuguangw/6265028633/\">Maria from the film Metropolis, on display at the Robot Hall of Fame</a>", "source": "commons-desc-page", "hidden": ""}, "Artist": {"value": "<a rel=\"nofollow\" class=\"external text\" href=\"https://www.flickr.com/people/32366606@N00\">Jiuguang Wang</a> from Pittsburgh, Pennsylvania, United States", "source": "commons-desc-page"}, "LicenseShortName": {"value": "CC BY-SA 2.0", "source": "commons-desc-page", "hidden": ""}, "UsageTerms": {"value": "Creative Commons Attribution-Share Alike 2.0", "source": "commons-desc-page", "hidden": ""}, "AttributionRequired": {"value": "true", "source": "commons-desc-page", "hidden": ""}, "LicenseUrl": {"value": "https://creativecommons.org/licenses/by-sa/2.0", "source": "commons-desc-page", "hidden": ""}, "Copyrighted": {"value": "True", "source": "commons-desc-page", "hidden": ""}, "Restrictions": {"value": "", "source": "commons-desc-page", "hidden": ""}, "License": {"value": "cc-by-sa-2.0", "source": "commons-templates", "hidden": ""}}}, {"kind": "restbase-original", "width": 210, "height": 475, "url": "https://upload.wikimedia.org/wikipedia/en/9/97/Metropolis_%28German_three-sheet_poster%29.jpg", "file": "File:Metropolis %28German three-sheet poster%29.jpg", "orig": "Metropolis_%28German_three-sheet_poster%29.jpg"}, {"kind": "restbase-thumb", "width": 141, "height": 320, "url": "https://upload.wikimedia.org/wikipedia/en/thumb/9/97/Metropolis_%28German_three-sheet_poster%29.jpg/141px-Metropolis_%28German_three-sheet_poster%29.jpg", "file": "File:141px-Metropolis %28German three-sheet poster%29.jpg", "orig": "141px-Metropolis_%28German_three-sheet_poster%29.jpg"}], "14_Singin'_in_the_Rain": [{"kind": "query-pageimage", "file": "File:Singin' in the Rain (1952 poster).jpg", "orig": "Singin'_in_the_Rain_(1952_poster).jpg", "timestamp": "2020-01-08T01:01:52Z", "size": 1541688, "width": 1937, "height": 2936, "url": "https://upload.wikimedia.org/wikipedia/commons/5/5d/Singin%27_in_the_Rain_%281952_poster%29.jpg", "descriptionurl": "https://commons.wikimedia.org/wiki/File:Singin%27_in_the_Rain_(1952_poster).jpg", "descriptionshorturl": "https://commons.wikimedia.org/w/index.php?curid=85710951", "title": "File:Singin' in the Rain (1952 poster).jpg", "metadata": {"DateTime": {"value": "2020-01-08 01:01:52", "source": "mediawiki-metadata", "hidden": ""}, "ObjectName": {"value": "Singin' in the Rain (1952 poster)", "source": "mediawiki-metadata", "hidden": ""}, "CommonsMetadataExtension": {"value": 1.2, "source": "extension", "hidden": ""}, "Categories": {"value": "Film posters of the United States, 1952|PD-Art (PD-US-not renewed)|PD US not renewed|Singin' in the Rain (film)", "source": "commons-categories", "hidden": ""}, "Assessments": {"value": "", "source": "commons-categories", "hidden": ""}, "ImageDescription": {"value": "Poster for the American theatrical run of the 1952 musical film <i><a href=\"https://en.wikipedia.org/wiki/Singin%27_in_the_Rain\" class=\"extiw\" title=\"w:Singin' in the Rain\">Singin' in the Rain</a></i>.", "source": "commons-desc-page"}, "DateTimeOriginal": {"value": "1952", "source": "commons-desc-page"}, "Credit": {"value": "Scan via <a rel=\"nofollow\" class=\"external text\" href=\"https://movieposters.ha.com/itm/musical/singin-in-the-rain-mgm-1952-one-sheet-27-x-41-/a/7055-83341.s\">Heritage Auctions</a>. Cropped from the original image.", "source": "commons-desc-page", "hidden": ""}, "Artist": {"value": "\"Copyright 1952 <a href=\"https://en.wikipedia.org/wiki/Loews_Cineplex_Entertainment\" class=\"extiw\" title=\"w:Loews Cineplex Entertainment\">Loew's Incorporated</a>\"", "source": "commons-desc-page"}, "Permission": {"value": "The poster included a valid copyright notice, seen at bottom left. However, the copyright for the artwork was not renewed, as was required by American copyright law to extend/maintain protection for works published 1963 or earlier. See the <a rel=\"nofollow\" class=\"external text\" href=\"https://cocatalog.loc.gov/cgi-bin/Pwebrecon.cgi?DB=local&amp;PAGE=First\">Copyright Catalog (1978 to present)</a>. In order to maintain copyright protection, the poster would have had to be renewed 28 years after publication. Because it was not renewed, copyright lapsed at that time. Note that the poster art is a distinct work from the film it represents and had to be renewed separately.\n(N.B.: There is a registration (Reg. No. <a rel=\"nofollow\" class=\"external text\" href=\"https://cocatalog.loc.gov/cgi-bin/Pwebrecon.cgi?Search_Arg=VA0001309427&amp;Search_Code=REGS&amp;PID=IsEOWqeS516Be8EOl88zN99nUuq7KV&amp;SEQ=20200107194709&amp;CNT=25&amp;HIST=1\">VA0001309427</a>, 2002-12-02) for \"Singin in the rain collection\", a work published 1998-05-10, with \"Preexisting material: movie posters\" and \"New Matter: changes &amp; additional artwork.\" This registration appears to have been made for some modified versions of <i>Singin' in the Rain</i> promotional artwork, likely including this poster, probably to coincide with a home-video release, a book, or some other new republication of the material. It is <i><b>not</b></i> to be confused with a <i>renewal</i> of the original poster art, and in any event it would have come too late: the 1952 poster had to be renewed in 1979 or 1980, expiring thereafter, while this registration came in 2002 for a 1998 publication. These later, modified versions of the poster artwork may be protected by copyright, but even so these works would be distinct from the original unmodified poster as presented here.)", "source": "commons-desc-page", "hidden": ""}, "LicenseShortName": {"value": "Public domain", "source": "commons-desc-page", "hidden": ""}, "UsageTerms": {"value": "Public domain", "source": "commons-desc-page", "hidden": ""}, "AttributionRequired": {"value": "false", "source": "commons-desc-page", "hidden": ""}, "Copyrighted": {"value": "False", "source": "commons-desc-page", "hidden": ""}, "Restrictions": {"value": "", "source": "commons-desc-page", "hidden": ""}, "License": {"value": "pd", "source": "commons-templates", "hidden": ""}}}, {"kind": "query-thumbnail", "width": 158, "height": 240, "url": "https://upload.wikimedia.org/wikipedia/commons/thumb/5/5d/Singin%27_in_the_Rain_%281952_poster%29.jpg/158px-Singin%27_in_the_Rain_%281952_poster%29.jpg", "file": "File:Singin%27 in the Rain %281952 poster%29.jpg", "orig": "Singin%27_in_the_Rain_%281952_poster%29.jpg"}, {"kind": "parse-image", "file": "File:Singin' in the Rain (1952 poster).jpg", "orig": "Singin' in the Rain (1952 poster).jpg", "timestamp": "2020-01-08T01:01:52Z", "size": 1541688, "width": 1937, "height": 2936, "url": "https://upload.wikimedia.org/wikipedia/commons/5/5d/Singin%27_in_the_Rain_%281952_poster%29.jpg", "descriptionurl": "https://commons.wikimedia.org/wiki/File:Singin%27_in_the_Rain_(1952_poster).jpg", "descriptionshorturl": "https://commons.wikimedia.org/w/index.php?curid=85710951", "title": "File:Singin' in the Rain (1952 poster).jpg", "metadata": {"DateTime": {"value": "2020-01-08 01:01:52", "source": "mediawiki-metadata", "hidden": ""}, "ObjectName": {"value": "Singin' in the Rain (1952 poster)", "source": "mediawiki-metadata", "hidden": ""}, "CommonsMetadataExtension": {"value": 1.2, "source": "extension", "hidden": ""}, "Categories": {"value": "Film posters of the United States, 1952|PD-Art (PD-US-not renewed)|PD US not renewed|Singin' in the Rain (film)", "source": "commons-categories", "hidden": ""}, "Assessments": {"value": "", "source": "commons-categories", "hidden": ""}, "ImageDescription": {"value": "Poster for the American theatrical run of the 1952 musical film <i><a href=\"https://en.wikipedia.org/wiki/Singin%27_in_the_Rain\" class=\"extiw\" title=\"w:Singin' in the Rain\">Singin' in the Rain</a></i>.", "source": "commons-desc-page"}, "DateTimeOriginal": {"value": "1952", "source": "commons-desc-page"}, "Credit": {"value": "Scan via <a rel=\"nofollow\" class=\"external text\" href=\"https://movieposters.ha.com/itm/musical/singin-in-the-rain-mgm-1952-one-sheet-27-x-41-/a/7055-83341.s\">Heritage Auctions</a>. Cropped from the original image.", "source": "commons-desc-page", "hidden": ""}, "Artist": {"value": "\"Copyright 1952 <a href=\"https://en.wikipedia.org/wiki/Loews_Cineplex_Entertainment\" class=\"extiw\" title=\"w:Loews Cineplex Entertainment\">Loew's Incorporated</a>\"", "source": "commons-desc-page"}, "Permission": {"value": "The poster included a valid copyright notice, seen at bottom left. However, the copyright for the artwork was not renewed, as was required by American copyright law to extend/maintain protection for works published 1963 or earlier. See the <a rel=\"nofollow\" class=\"external text\" href=\"https://cocatalog.loc.gov/cgi-bin/Pwebrecon.cgi?DB=local&amp;PAGE=First\">Copyright Catalog (1978 to present)</a>. In order to maintain copyright protection, the poster would have had to be renewed 28 years after publication. Because it was not renewed, copyright lapsed at that time. Note that the poster art is a distinct work from the film it represents and had to be renewed separately.\n(N.B.: There is a registration (Reg. No. <a rel=\"nofollow\" class=\"external text\" href=\"https://cocatalog.loc.gov/cgi-bin/Pwebrecon.cgi?Search_Arg=VA0001309427&amp;Search_Code=REGS&amp;PID=IsEOWqeS516Be8EOl88zN99nUuq7KV&amp;SEQ=20200107194709&amp;CNT=25&amp;HIST=1\">VA0001309427</a>, 2002-12-02) for \"Singin in the rain collection\", a work published 1998-05-10, with \"Preexisting material: movie posters\" and \"New Matter: changes &amp; additional artwork.\" This registration appears to have been made for some modified versions of <i>Singin' in the Rain</i> promotional artwork, likely including this poster, probably to coincide with a home-video release, a book, or some other new republication of the material. It is <i><b>not</b></i> to be confused with a <i>renewal</i> of the original poster art, and in any event it would have come too late: the 1952 poster had to be renewed in 1979 or 1980, expiring thereafter, while this registration came in 2002 for a 1998 publication. These later, modified versions of the poster artwork may be protected by copyright, but even so these works would be distinct from the original unmodified poster as presented here.)", "source": "commons-desc-page", "hidden": ""}, "LicenseShortName": {"value": "Public domain", "source": "commons-desc-page", "hidden": ""}, "UsageTerms": {"value": "Public domain", "source": "commons-desc-page", "hidden": ""}, "AttributionRequired": {"value": "false", "source": "commons-desc-page", "hidden": ""}, "Copyrighted": {"value": "False", "source": "commons-desc-page", "hidden": ""}, "Restrictions": {"value": "", "source": "commons-desc-page", "hidden": ""}, "License": {"value": "pd", "source": "commons-templates", "hidden": ""}}}, {"file": "File:Singin' in the Rain (1952 poster).jpg", "kind": "wikidata-image", "orig": "Singin' in the Rain (1952 poster).jpg", "timestamp": "2020-01-08T01:01:52Z", "size": 1541688, "width": 1937, "height": 2936, "url": "https://upload.wikimedia.org/wikipedia/commons/5/5d/Singin%27_in_the_Rain_%281952_poster%29.jpg", "descriptionurl": "https://commons.wikimedia.org/wiki/File:Singin%27_in_the_Rain_(1952_poster).jpg", "descriptionshorturl": "https://commons.wikimedia.org/w/index.php?curid=85710951", "title": "File:Singin' in the Rain (1952 poster).jpg", "metadata": {"DateTime": {"value": "2020-01-08 01:01:52", "source": "mediawiki-metadata", "hidden": ""}, "ObjectName": {"value": "Singin' in the Rain (1952 poster)", "source": "mediawiki-metadata", "hidden": ""}, "CommonsMetadataExtension": {"value": 1.2, "source": "extension", "hidden": ""}, "Categories": {"value": "Film posters of the United States, 1952|PD-Art (PD-US-not renewed)|PD US not renewed|Singin' in the Rain (film)", "source": "commons-categories", "hidden": ""}, "Assessments": {"value": "", "source": "commons-categories", "hidden": ""}, "ImageDescription": {"value": "Poster for the American theatrical run of the 1952 musical film <i><a href=\"https://en.wikipedia.org/wiki/Singin%27_in_the_Rain\" class=\"extiw\" title=\"w:Singin' in the Rain\">Singin' in the Rain</a></i>.", "source": "commons-desc-page"}, "DateTimeOriginal": {"value": "1952", "source": "commons-desc-page"}, "Credit": {"value": "Scan via <a rel=\"nofollow\" class=\"external text\" href=\"https://movieposters.ha.com/itm/musical/singin-in-the-rain-mgm-1952-one-sheet-27-x-41-/a/7055-83341.s\">Heritage Auctions</a>. Cropped from the original image.", "source": "commons-desc-page", "hidden": ""}, "Artist": {"value": "\"Copyright 1952 <a href=\"https://en.wikipedia.org/wiki/Loews_Cineplex_Entertainment\" class=\"extiw\" title=\"w:Loews Cineplex Entertainment\">Loew's Incorporated</a>\"", "source": "commons-desc-page"}, "Permission": {"value": "The poster included a valid copyright notice, seen at bottom left. However, the copyright for the artwork was not renewed, as was required by American copyright law to extend/maintain protection for works published 1963 or earlier. See the <a rel=\"nofollow\" class=\"external text\" href=\"https://cocatalog.loc.gov/cgi-bin/Pwebrecon.cgi?DB=local&amp;PAGE=First\">Copyright Catalog (1978 to present)</a>. In order to maintain copyright protection, the poster would have had to be renewed 28 years after publication. Because it was not renewed, copyright lapsed at that time. Note that the poster art is a distinct work from the film it represents and had to be renewed separately.\n(N.B.: There is a registration (Reg. No. <a rel=\"nofollow\" class=\"external text\" href=\"https://cocatalog.loc.gov/cgi-bin/Pwebrecon.cgi?Search_Arg=VA0001309427&amp;Search_Code=REGS&amp;PID=IsEOWqeS516Be8EOl88zN99nUuq7KV&amp;SEQ=20200107194709&amp;CNT=25&amp;HIST=1\">VA0001309427</a>, 2002-12-02) for \"Singin in the rain collection\", a work published 1998-05-10, with \"Preexisting material: movie posters\" and \"New Matter: changes &amp; additional artwork.\" This registration appears to have been made for some modified versions of <i>Singin' in the Rain</i> promotional artwork, likely including this poster, probably to coincide with a home-video release, a book, or some other new republication of the material. It is <i><b>not</b></i> to be confused with a <i>renewal</i> of the original poster art, and in any event it would have come too late: the 1952 poster had to be renewed in 1979 or 1980, expiring thereafter, while this registration came in 2002 for a 1998 publication. These later, modified versions of the poster artwork may be protected by copyright, but even so these works would be distinct from the original unmodified poster as presented here.)", "source": "commons-desc-page", "hidden": ""}, "LicenseShortName": {"value": "Public domain", "source": "commons-desc-page", "hidden": ""}, "UsageTerms": {"value": "Public domain", "source": "commons-desc-page", "hidden": ""}, "AttributionRequired": {"value": "false", "source": "commons-desc-page", "hidden": ""}, "Copyrighted": {"value": "False", "source": "commons-desc-page", "hidden": ""}, "Restrictions": {"value": "", "source": "commons-desc-page", "hidden": ""}, "License": {"value": "pd", "source": "commons-templates", "hidden": ""}}}, {"kind": "restbase-original", "width": 1937, "height": 2936, "url": "https://upload.wikimedia.org/wikipedia/commons/5/5d/Singin%27_in_the_Rain_%281952_poster%29.jpg", "file": "File:Singin%27 in the Rain %281952 poster%29.jpg", "orig": "Singin%27_in_the_Rain_%281952_poster%29.jpg"}, {"kind": "restbase-thumb", "width": 211, "height": 320, "url": "https://upload.wikimedia.org/wikipedia/commons/thumb/5/5d/Singin%27_in_the_Rain_%281952_poster%29.jpg/211px-Singin%27_in_the_Rain_%281952_poster%29.jpg", "file": "File:211px-Singin%27 in the Rain %281952 poster%29.jpg", "orig": "211px-Singin%27_in_the_Rain_%281952_poster%29.jpg"}], "15_Boyhood_(film)": [{"kind": "query-pageimage", "file": "File:Singin' in the Rain (1952 poster).jpg", "orig": "Singin'_in_the_Rain_(1952_poster).jpg", "timestamp": "2020-01-08T01:01:52Z", "size": 1541688, "width": 1937, "height": 2936, "url": "https://upload.wikimedia.org/wikipedia/commons/5/5d/Singin%27_in_the_Rain_%281952_poster%29.jpg", "descriptionurl": "https://commons.wikimedia.org/wiki/File:Singin%27_in_the_Rain_(1952_poster).jpg", "descriptionshorturl": "https://commons.wikimedia.org/w/index.php?curid=85710951", "title": "File:Singin' in the Rain (1952 poster).jpg", "metadata": {"DateTime": {"value": "2020-01-08 01:01:52", "source": "mediawiki-metadata", "hidden": ""}, "ObjectName": {"value": "Singin' in the Rain (1952 poster)", "source": "mediawiki-metadata", "hidden": ""}, "CommonsMetadataExtension": {"value": 1.2, "source": "extension", "hidden": ""}, "Categories": {"value": "Film posters of the United States, 1952|PD-Art (PD-US-not renewed)|PD US not renewed|Singin' in the Rain (film)", "source": "commons-categories", "hidden": ""}, "Assessments": {"value": "", "source": "commons-categories", "hidden": ""}, "ImageDescription": {"value": "Poster for the American theatrical run of the 1952 musical film <i><a href=\"https://en.wikipedia.org/wiki/Singin%27_in_the_Rain\" class=\"extiw\" title=\"w:Singin' in the Rain\">Singin' in the Rain</a></i>.", "source": "commons-desc-page"}, "DateTimeOriginal": {"value": "1952", "source": "commons-desc-page"}, "Credit": {"value": "Scan via <a rel=\"nofollow\" class=\"external text\" href=\"https://movieposters.ha.com/itm/musical/singin-in-the-rain-mgm-1952-one-sheet-27-x-41-/a/7055-83341.s\">Heritage Auctions</a>. Cropped from the original image.", "source": "commons-desc-page", "hidden": ""}, "Artist": {"value": "\"Copyright 1952 <a href=\"https://en.wikipedia.org/wiki/Loews_Cineplex_Entertainment\" class=\"extiw\" title=\"w:Loews Cineplex Entertainment\">Loew's Incorporated</a>\"", "source": "commons-desc-page"}, "Permission": {"value": "The poster included a valid copyright notice, seen at bottom left. However, the copyright for the artwork was not renewed, as was required by American copyright law to extend/maintain protection for works published 1963 or earlier. See the <a rel=\"nofollow\" class=\"external text\" href=\"https://cocatalog.loc.gov/cgi-bin/Pwebrecon.cgi?DB=local&amp;PAGE=First\">Copyright Catalog (1978 to present)</a>. In order to maintain copyright protection, the poster would have had to be renewed 28 years after publication. Because it was not renewed, copyright lapsed at that time. Note that the poster art is a distinct work from the film it represents and had to be renewed separately.\n(N.B.: There is a registration (Reg. No. <a rel=\"nofollow\" class=\"external text\" href=\"https://cocatalog.loc.gov/cgi-bin/Pwebrecon.cgi?Search_Arg=VA0001309427&amp;Search_Code=REGS&amp;PID=IsEOWqeS516Be8EOl88zN99nUuq7KV&amp;SEQ=20200107194709&amp;CNT=25&amp;HIST=1\">VA0001309427</a>, 2002-12-02) for \"Singin in the rain collection\", a work published 1998-05-10, with \"Preexisting material: movie posters\" and \"New Matter: changes &amp; additional artwork.\" This registration appears to have been made for some modified versions of <i>Singin' in the Rain</i> promotional artwork, likely including this poster, probably to coincide with a home-video release, a book, or some other new republication of the material. It is <i><b>not</b></i> to be confused with a <i>renewal</i> of the original poster art, and in any event it would have come too late: the 1952 poster had to be renewed in 1979 or 1980, expiring thereafter, while this registration came in 2002 for a 1998 publication. These later, modified versions of the poster artwork may be protected by copyright, but even so these works would be distinct from the original unmodified poster as presented here.)", "source": "commons-desc-page", "hidden": ""}, "LicenseShortName": {"value": "Public domain", "source": "commons-desc-page", "hidden": ""}, "UsageTerms": {"value": "Public domain", "source": "commons-desc-page", "hidden": ""}, "AttributionRequired": {"value": "false", "source": "commons-desc-page", "hidden": ""}, "Copyrighted": {"value": "False", "source": "commons-desc-page", "hidden": ""}, "Restrictions": {"value": "", "source": "commons-desc-page", "hidden": ""}, "License": {"value": "pd", "source": "commons-templates", "hidden": ""}}}, {"kind": "query-thumbnail", "width": 158, "height": 240, "url": "https://upload.wikimedia.org/wikipedia/commons/thumb/5/5d/Singin%27_in_the_Rain_%281952_poster%29.jpg/158px-Singin%27_in_the_Rain_%281952_poster%29.jpg", "file": "File:Singin%27 in the Rain %281952 poster%29.jpg", "orig": "Singin%27_in_the_Rain_%281952_poster%29.jpg"}, {"kind": "parse-image", "file": "File:Singin' in the Rain (1952 poster).jpg", "orig": "Singin' in the Rain (1952 poster).jpg", "timestamp": "2020-01-08T01:01:52Z", "size": 1541688, "width": 1937, "height": 2936, "url": "https://upload.wikimedia.org/wikipedia/commons/5/5d/Singin%27_in_the_Rain_%281952_poster%29.jpg", "descriptionurl": "https://commons.wikimedia.org/wiki/File:Singin%27_in_the_Rain_(1952_poster).jpg", "descriptionshorturl": "https://commons.wikimedia.org/w/index.php?curid=85710951", "title": "File:Singin' in the Rain (1952 poster).jpg", "metadata": {"DateTime": {"value": "2020-01-08 01:01:52", "source": "mediawiki-metadata", "hidden": ""}, "ObjectName": {"value": "Singin' in the Rain (1952 poster)", "source": "mediawiki-metadata", "hidden": ""}, "CommonsMetadataExtension": {"value": 1.2, "source": "extension", "hidden": ""}, "Categories": {"value": "Film posters of the United States, 1952|PD-Art (PD-US-not renewed)|PD US not renewed|Singin' in the Rain (film)", "source": "commons-categories", "hidden": ""}, "Assessments": {"value": "", "source": "commons-categories", "hidden": ""}, "ImageDescription": {"value": "Poster for the American theatrical run of the 1952 musical film <i><a href=\"https://en.wikipedia.org/wiki/Singin%27_in_the_Rain\" class=\"extiw\" title=\"w:Singin' in the Rain\">Singin' in the Rain</a></i>.", "source": "commons-desc-page"}, "DateTimeOriginal": {"value": "1952", "source": "commons-desc-page"}, "Credit": {"value": "Scan via <a rel=\"nofollow\" class=\"external text\" href=\"https://movieposters.ha.com/itm/musical/singin-in-the-rain-mgm-1952-one-sheet-27-x-41-/a/7055-83341.s\">Heritage Auctions</a>. Cropped from the original image.", "source": "commons-desc-page", "hidden": ""}, "Artist": {"value": "\"Copyright 1952 <a href=\"https://en.wikipedia.org/wiki/Loews_Cineplex_Entertainment\" class=\"extiw\" title=\"w:Loews Cineplex Entertainment\">Loew's Incorporated</a>\"", "source": "commons-desc-page"}, "Permission": {"value": "The poster included a valid copyright notice, seen at bottom left. However, the copyright for the artwork was not renewed, as was required by American copyright law to extend/maintain protection for works published 1963 or earlier. See the <a rel=\"nofollow\" class=\"external text\" href=\"https://cocatalog.loc.gov/cgi-bin/Pwebrecon.cgi?DB=local&amp;PAGE=First\">Copyright Catalog (1978 to present)</a>. In order to maintain copyright protection, the poster would have had to be renewed 28 years after publication. Because it was not renewed, copyright lapsed at that time. Note that the poster art is a distinct work from the film it represents and had to be renewed separately.\n(N.B.: There is a registration (Reg. No. <a rel=\"nofollow\" class=\"external text\" href=\"https://cocatalog.loc.gov/cgi-bin/Pwebrecon.cgi?Search_Arg=VA0001309427&amp;Search_Code=REGS&amp;PID=IsEOWqeS516Be8EOl88zN99nUuq7KV&amp;SEQ=20200107194709&amp;CNT=25&amp;HIST=1\">VA0001309427</a>, 2002-12-02) for \"Singin in the rain collection\", a work published 1998-05-10, with \"Preexisting material: movie posters\" and \"New Matter: changes &amp; additional artwork.\" This registration appears to have been made for some modified versions of <i>Singin' in the Rain</i> promotional artwork, likely including this poster, probably to coincide with a home-video release, a book, or some other new republication of the material. It is <i><b>not</b></i> to be confused with a <i>renewal</i> of the original poster art, and in any event it would have come too late: the 1952 poster had to be renewed in 1979 or 1980, expiring thereafter, while this registration came in 2002 for a 1998 publication. These later, modified versions of the poster artwork may be protected by copyright, but even so these works would be distinct from the original unmodified poster as presented here.)", "source": "commons-desc-page", "hidden": ""}, "LicenseShortName": {"value": "Public domain", "source": "commons-desc-page", "hidden": ""}, "UsageTerms": {"value": "Public domain", "source": "commons-desc-page", "hidden": ""}, "AttributionRequired": {"value": "false", "source": "commons-desc-page", "hidden": ""}, "Copyrighted": {"value": "False", "source": "commons-desc-page", "hidden": ""}, "Restrictions": {"value": "", "source": "commons-desc-page", "hidden": ""}, "License": {"value": "pd", "source": "commons-templates", "hidden": ""}}}, {"file": "File:Singin' in the Rain (1952 poster).jpg", "kind": "wikidata-image", "orig": "Singin' in the Rain (1952 poster).jpg", "timestamp": "2020-01-08T01:01:52Z", "size": 1541688, "width": 1937, "height": 2936, "url": "https://upload.wikimedia.org/wikipedia/commons/5/5d/Singin%27_in_the_Rain_%281952_poster%29.jpg", "descriptionurl": "https://commons.wikimedia.org/wiki/File:Singin%27_in_the_Rain_(1952_poster).jpg", "descriptionshorturl": "https://commons.wikimedia.org/w/index.php?curid=85710951", "title": "File:Singin' in the Rain (1952 poster).jpg", "metadata": {"DateTime": {"value": "2020-01-08 01:01:52", "source": "mediawiki-metadata", "hidden": ""}, "ObjectName": {"value": "Singin' in the Rain (1952 poster)", "source": "mediawiki-metadata", "hidden": ""}, "CommonsMetadataExtension": {"value": 1.2, "source": "extension", "hidden": ""}, "Categories": {"value": "Film posters of the United States, 1952|PD-Art (PD-US-not renewed)|PD US not renewed|Singin' in the Rain (film)", "source": "commons-categories", "hidden": ""}, "Assessments": {"value": "", "source": "commons-categories", "hidden": ""}, "ImageDescription": {"value": "Poster for the American theatrical run of the 1952 musical film <i><a href=\"https://en.wikipedia.org/wiki/Singin%27_in_the_Rain\" class=\"extiw\" title=\"w:Singin' in the Rain\">Singin' in the Rain</a></i>.", "source": "commons-desc-page"}, "DateTimeOriginal": {"value": "1952", "source": "commons-desc-page"}, "Credit": {"value": "Scan via <a rel=\"nofollow\" class=\"external text\" href=\"https://movieposters.ha.com/itm/musical/singin-in-the-rain-mgm-1952-one-sheet-27-x-41-/a/7055-83341.s\">Heritage Auctions</a>. Cropped from the original image.", "source": "commons-desc-page", "hidden": ""}, "Artist": {"value": "\"Copyright 1952 <a href=\"https://en.wikipedia.org/wiki/Loews_Cineplex_Entertainment\" class=\"extiw\" title=\"w:Loews Cineplex Entertainment\">Loew's Incorporated</a>\"", "source": "commons-desc-page"}, "Permission": {"value": "The poster included a valid copyright notice, seen at bottom left. However, the copyright for the artwork was not renewed, as was required by American copyright law to extend/maintain protection for works published 1963 or earlier. See the <a rel=\"nofollow\" class=\"external text\" href=\"https://cocatalog.loc.gov/cgi-bin/Pwebrecon.cgi?DB=local&amp;PAGE=First\">Copyright Catalog (1978 to present)</a>. In order to maintain copyright protection, the poster would have had to be renewed 28 years after publication. Because it was not renewed, copyright lapsed at that time. Note that the poster art is a distinct work from the film it represents and had to be renewed separately.\n(N.B.: There is a registration (Reg. No. <a rel=\"nofollow\" class=\"external text\" href=\"https://cocatalog.loc.gov/cgi-bin/Pwebrecon.cgi?Search_Arg=VA0001309427&amp;Search_Code=REGS&amp;PID=IsEOWqeS516Be8EOl88zN99nUuq7KV&amp;SEQ=20200107194709&amp;CNT=25&amp;HIST=1\">VA0001309427</a>, 2002-12-02) for \"Singin in the rain collection\", a work published 1998-05-10, with \"Preexisting material: movie posters\" and \"New Matter: changes &amp; additional artwork.\" This registration appears to have been made for some modified versions of <i>Singin' in the Rain</i> promotional artwork, likely including this poster, probably to coincide with a home-video release, a book, or some other new republication of the material. It is <i><b>not</b></i> to be confused with a <i>renewal</i> of the original poster art, and in any event it would have come too late: the 1952 poster had to be renewed in 1979 or 1980, expiring thereafter, while this registration came in 2002 for a 1998 publication. These later, modified versions of the poster artwork may be protected by copyright, but even so these works would be distinct from the original unmodified poster as presented here.)", "source": "commons-desc-page", "hidden": ""}, "LicenseShortName": {"value": "Public domain", "source": "commons-desc-page", "hidden": ""}, "UsageTerms": {"value": "Public domain", "source": "commons-desc-page", "hidden": ""}, "AttributionRequired": {"value": "false", "source": "commons-desc-page", "hidden": ""}, "Copyrighted": {"value": "False", "source": "commons-desc-page", "hidden": ""}, "Restrictions": {"value": "", "source": "commons-desc-page", "hidden": ""}, "License": {"value": "pd", "source": "commons-templates", "hidden": ""}}}, {"kind": "restbase-original", "width": 1937, "height": 2936, "url": "https://upload.wikimedia.org/wikipedia/commons/5/5d/Singin%27_in_the_Rain_%281952_poster%29.jpg", "file": "File:Singin%27 in the Rain %281952 poster%29.jpg", "orig": "Singin%27_in_the_Rain_%281952_poster%29.jpg"}, {"kind": "restbase-thumb", "width": 211, "height": 320, "url": "https://upload.wikimedia.org/wikipedia/commons/thumb/5/5d/Singin%27_in_the_Rain_%281952_poster%29.jpg/211px-Singin%27_in_the_Rain_%281952_poster%29.jpg", "file": "File:211px-Singin%27 in the Rain %281952 poster%29.jpg", "orig": "211px-Singin%27_in_the_Rain_%281952_poster%29.jpg"}], "22_A_Hard_Day%27s_Night_(film)": [{"kind": "parse-image", "file": "File:Snow White 1937 poster.png", "orig": "Snow White 1937 poster.png", "timestamp": "2017-12-14T06:39:55Z", "size": 195583, "width": 259, "height": 385, "url": "https://upload.wikimedia.org/wikipedia/en/4/49/Snow_White_1937_poster.png", "descriptionurl": "https://en.wikipedia.org/wiki/File:Snow_White_1937_poster.png", "descriptionshorturl": "https://en.wikipedia.org/w/index.php?curid=40982148", "title": "File:Snow White 1937 poster.png", "metadata": {"DateTime": {"value": "2017-12-14 06:39:55", "source": "mediawiki-metadata", "hidden": ""}, "ObjectName": {"value": "Snow White 1937 poster", "source": "mediawiki-metadata", "hidden": ""}, "CommonsMetadataExtension": {"value": 1.2, "source": "extension", "hidden": ""}, "Categories": {"value": "All non-free media|Fair use images of film posters|Files with no machine-readable author|Files with no machine-readable description|Files with no machine-readable source|Noindexed pages|Non-free posters|Walt Disney film posters|Wikipedia non-free files for NFUR review", "source": "commons-categories", "hidden": ""}, "Assessments": {"value": "", "source": "commons-categories", "hidden": ""}, "LicenseShortName": {"value": "Fair use", "source": "commons-desc-page", "hidden": ""}, "NonFree": {"value": "true", "source": "commons-desc-page", "hidden": ""}, "Restrictions": {"value": "", "source": "commons-desc-page", "hidden": ""}}}, {"file": "File:Snow white 1937 trailer screenshot.jpg", "kind": "wikidata-image", "orig": "Snow white 1937 trailer screenshot.jpg", "timestamp": "2005-12-13T20:36:02Z", "size": 81317, "width": 720, "height": 576, "url": "https://upload.wikimedia.org/wikipedia/commons/b/b0/Snow_white_1937_trailer_screenshot.jpg", "descriptionurl": "https://commons.wikimedia.org/wiki/File:Snow_white_1937_trailer_screenshot.jpg", "descriptionshorturl": "https://commons.wikimedia.org/w/index.php?curid=459812", "title": "File:Snow white 1937 trailer screenshot.jpg", "metadata": {"DateTime": {"value": "2005-12-13 20:36:02", "source": "mediawiki-metadata", "hidden": ""}, "ObjectName": {"value": "Snow white 1937 trailer screenshot", "source": "mediawiki-metadata", "hidden": ""}, "CommonsMetadataExtension": {"value": 1.2, "source": "extension", "hidden": ""}, "Categories": {"value": "Files with no machine-readable author|Files with no machine-readable source|Intertitles|Media missing infobox template|PD US not renewed|Snow White and the Seven Dwarfs (trailer screenshots)", "source": "commons-categories", "hidden": ""}, "Assessments": {"value": "", "source": "commons-categories", "hidden": ""}, "LicenseShortName": {"value": "Public domain", "source": "commons-desc-page", "hidden": ""}, "UsageTerms": {"value": "Public domain", "source": "commons-desc-page", "hidden": ""}, "AttributionRequired": {"value": "false", "source": "commons-desc-page", "hidden": ""}, "Copyrighted": {"value": "False", "source": "commons-desc-page", "hidden": ""}, "Restrictions": {"value": "", "source": "commons-desc-page", "hidden": ""}, "License": {"value": "pd", "source": "commons-templates", "hidden": ""}}}, {"kind": "restbase-original", "width": 259, "height": 385, "url": "https://upload.wikimedia.org/wikipedia/en/4/49/Snow_White_1937_poster.png", "file": "File:Snow White 1937 poster.png", "orig": "Snow_White_1937_poster.png"}, {"kind": "restbase-thumb", "width": 215, "height": 320, "url": "https://upload.wikimedia.org/wikipedia/en/thumb/4/49/Snow_White_1937_poster.png/215px-Snow_White_1937_poster.png", "file": "File:215px-Snow White 1937 poster.png", "orig": "215px-Snow_White_1937_poster.png"}], "40_Argo_(2012_film)": [{"kind": "parse-image", "file": "File:Toy Story 3 poster.jpg", "orig": "Toy Story 3 poster.jpg", "timestamp": "2016-12-05T20:20:36Z", "size": 170860, "width": 220, "height": 326, "url": "https://upload.wikimedia.org/wikipedia/en/6/69/Toy_Story_3_poster.jpg", "descriptionurl": "https://en.wikipedia.org/wiki/File:Toy_Story_3_poster.jpg", "descriptionshorturl": "https://en.wikipedia.org/w/index.php?curid=28435474", "title": "File:Toy Story 3 poster.jpg", "metadata": {"DateTime": {"value": "2016-12-05 20:20:36", "source": "mediawiki-metadata", "hidden": ""}, "ObjectName": {"value": "Toy Story 3 poster", "source": "mediawiki-metadata", "hidden": ""}, "CommonsMetadataExtension": {"value": 1.2, "source": "extension", "hidden": ""}, "Categories": {"value": "All non-free media|Animated film posters|Files with no machine-readable author|Noindexed pages|Non-free posters|Pixar film posters|Walt Disney film posters|Wikipedia non-free files with NFUR stated|Wikipedia non-free files with valid backlink", "source": "commons-categories", "hidden": ""}, "Assessments": {"value": "", "source": "commons-categories", "hidden": ""}, "ImageDescription": {"value": "<p>This is a poster for  <i>Toy Story 3</i>. <br>The poster art copyright is believed to belong to the distributor of the film, <a href=\"//en.wikipedia.org/wiki/Walt_Disney_Pictures\" title=\"Walt Disney Pictures\">Walt Disney Pictures</a>,  the publisher of the film or the graphic artist.\n</p>", "source": "commons-desc-page"}, "Credit": {"value": "<p><a rel=\"nofollow\" class=\"external text\" href=\"https://www.facebook.com/photo.php?fbid=343488809129&amp;set=pb.10498014129.-2207520000.1385487030.&amp;type=3&amp;theater\">Toy Story 3</a> on <a href=\"//en.wikipedia.org/wiki/Facebook\" title=\"Facebook\">Facebook</a>\n</p>", "source": "commons-desc-page", "hidden": ""}, "LicenseShortName": {"value": "Fair use", "source": "commons-desc-page", "hidden": ""}, "UsageTerms": {"value": "<a href=\"//en.wikipedia.org/wiki/Wikipedia:Non-free_use_rationale_guideline\" title=\"Wikipedia:Non-free use rationale guideline\">Fair use</a> of copyrighted material in the context of <a href=\"//en.wikipedia.org/wiki/Toy_Story_3\" title=\"Toy Story 3\">Toy Story 3</a>", "source": "commons-desc-page", "hidden": ""}, "Attribution": {"value": "<p><a rel=\"nofollow\" class=\"external text\" href=\"https://www.facebook.com/photo.php?fbid=343488809129&amp;set=pb.10498014129.-2207520000.1385487030.&amp;type=3&amp;theater\">Toy Story 3</a> on <a href=\"//en.wikipedia.org/wiki/Facebook\" title=\"Facebook\">Facebook</a>\n</p>", "source": "commons-desc-page", "hidden": ""}, "LicenseUrl": {"value": "//en.wikipedia.org/wiki/File:Toy_Story_3_poster.jpg", "source": "commons-desc-page", "hidden": ""}, "NonFree": {"value": "true", "source": "commons-desc-page", "hidden": ""}, "Copyrighted": {"value": "True", "source": "commons-desc-page", "hidden": ""}, "Restrictions": {"value": "", "source": "commons-desc-page", "hidden": ""}}}, {"kind": "restbase-original", "width": 220, "height": 326, "url": "https://upload.wikimedia.org/wikipedia/en/6/69/Toy_Story_3_poster.jpg", "file": "File:Toy Story 3 poster.jpg", "orig": "Toy_Story_3_poster.jpg"}, {"kind": "restbase-thumb", "width": 216, "height": 320, "url": "https://upload.wikimedia.org/wikipedia/en/thumb/6/69/Toy_Story_3_poster.jpg/216px-Toy_Story_3_poster.jpg", "file": "File:216px-Toy Story 3 poster.jpg", "orig": "216px-Toy_Story_3_poster.jpg"}], "72_Rosemary%27s_Baby_(film)": [{"kind": "query-pageimage", "file": "File:Rebecca (1939 poster).jpeg", "orig": "Rebecca_(1939_poster).jpeg", "timestamp": "2020-01-08T01:41:59Z", "size": 1322494, "width": 2013, "height": 3000, "url": "https://upload.wikimedia.org/wikipedia/commons/a/ad/Rebecca_%281939_poster%29.jpeg", "descriptionurl": "https://commons.wikimedia.org/wiki/File:Rebecca_(1939_poster).jpeg", "descriptionshorturl": "https://commons.wikimedia.org/w/index.php?curid=85711698", "title": "File:Rebecca (1939 poster).jpeg", "metadata": {"DateTime": {"value": "2020-01-08 01:41:59", "source": "mediawiki-metadata", "hidden": ""}, "ObjectName": {"value": "Rebecca (1939 poster)", "source": "mediawiki-metadata", "hidden": ""}, "CommonsMetadataExtension": {"value": 1.2, "source": "extension", "hidden": ""}, "Categories": {"value": "Film posters of the United States, 1940|PD-Art (PD-US-not renewed)|PD US not renewed|Rebecca (film)", "source": "commons-categories", "hidden": ""}, "Assessments": {"value": "", "source": "commons-categories", "hidden": ""}, "ImageDescription": {"value": "Theatrical poster for the American release of <a href=\"https://en.wikipedia.org/wiki/Alfred_Hitchcock\" class=\"extiw\" title=\"w:Alfred Hitchcock\">Alfred Hitchcock</a>'s 1940 film <i><a href=\"https://en.wikipedia.org/wiki/Rebecca_(1940_film)\" class=\"extiw\" title=\"w:Rebecca (1940 film)\">Rebecca</a></i>.", "source": "commons-desc-page"}, "DateTimeOriginal": {"value": "1939, per the copyright notice. Note that the film itself premiered March 1940. The poster was likely published in late 1939 to promote the film's coming release.", "source": "commons-desc-page"}, "Credit": {"value": "Scan via <a rel=\"nofollow\" class=\"external text\" href=\"https://movieposters.ha.com/itm/hitchcock/rebecca-united-artists-1940-one-sheet-275-x-41-/a/7109-87430.s?ic4=GalleryView-Thumbnail-071515\">Heritage Auctions</a>.", "source": "commons-desc-page", "hidden": ""}, "Artist": {"value": "\"\u00a9 1939 by <a href=\"https://en.wikipedia.org/wiki/United_Artists\" class=\"extiw\" title=\"w:United Artists\">United Artists Corporation</a>.\"", "source": "commons-desc-page"}, "Permission": {"value": "The poster included a valid copyright notice, seen at bottom left. However, the copyright for the artwork was not renewed, as was required by American copyright law to extend/maintain protection for works published 1963 or earlier. In order to maintain copyright protection, the poster would have had to be renewed 28 years after publication, in either <a rel=\"nofollow\" class=\"external text\" href=\"https://onlinebooks.library.upenn.edu/cce/1966r.html\">1966</a> or <a rel=\"nofollow\" class=\"external text\" href=\"https://onlinebooks.library.upenn.edu/cce/1967r.html\">1967</a> (see the sections for \"Artwork: Original registrations and renewals\" and refer to the links to search the copyright catalogs for those years). Because it was not renewed, copyright lapsed at that time. Note that the poster art is a distinct work from the film it represents and had to be renewed separately.", "source": "commons-desc-page", "hidden": ""}, "LicenseShortName": {"value": "Public domain", "source": "commons-desc-page", "hidden": ""}, "UsageTerms": {"value": "Public domain", "source": "commons-desc-page", "hidden": ""}, "AttributionRequired": {"value": "false", "source": "commons-desc-page", "hidden": ""}, "Copyrighted": {"value": "False", "source": "commons-desc-page", "hidden": ""}, "Restrictions": {"value": "", "source": "commons-desc-page", "hidden": ""}, "License": {"value": "pd", "source": "commons-templates", "hidden": ""}}}, {"kind": "query-thumbnail", "width": 161, "height": 240, "url": "https://upload.wikimedia.org/wikipedia/commons/thumb/a/ad/Rebecca_%281939_poster%29.jpeg/161px-Rebecca_%281939_poster%29.jpeg", "file": "File:Rebecca %281939 poster%29.jpeg", "orig": "Rebecca_%281939_poster%29.jpeg"}, {"kind": "parse-image", "file": "File:Rebecca (1939 poster).jpeg", "orig": "Rebecca (1939 poster).jpeg", "timestamp": "2020-01-08T01:41:59Z", "size": 1322494, "width": 2013, "height": 3000, "url": "https://upload.wikimedia.org/wikipedia/commons/a/ad/Rebecca_%281939_poster%29.jpeg", "descriptionurl": "https://commons.wikimedia.org/wiki/File:Rebecca_(1939_poster).jpeg", "descriptionshorturl": "https://commons.wikimedia.org/w/index.php?curid=85711698", "title": "File:Rebecca (1939 poster).jpeg", "metadata": {"DateTime": {"value": "2020-01-08 01:41:59", "source": "mediawiki-metadata", "hidden": ""}, "ObjectName": {"value": "Rebecca (1939 poster)", "source": "mediawiki-metadata", "hidden": ""}, "CommonsMetadataExtension": {"value": 1.2, "source": "extension", "hidden": ""}, "Categories": {"value": "Film posters of the United States, 1940|PD-Art (PD-US-not renewed)|PD US not renewed|Rebecca (film)", "source": "commons-categories", "hidden": ""}, "Assessments": {"value": "", "source": "commons-categories", "hidden": ""}, "ImageDescription": {"value": "Theatrical poster for the American release of <a href=\"https://en.wikipedia.org/wiki/Alfred_Hitchcock\" class=\"extiw\" title=\"w:Alfred Hitchcock\">Alfred Hitchcock</a>'s 1940 film <i><a href=\"https://en.wikipedia.org/wiki/Rebecca_(1940_film)\" class=\"extiw\" title=\"w:Rebecca (1940 film)\">Rebecca</a></i>.", "source": "commons-desc-page"}, "DateTimeOriginal": {"value": "1939, per the copyright notice. Note that the film itself premiered March 1940. The poster was likely published in late 1939 to promote the film's coming release.", "source": "commons-desc-page"}, "Credit": {"value": "Scan via <a rel=\"nofollow\" class=\"external text\" href=\"https://movieposters.ha.com/itm/hitchcock/rebecca-united-artists-1940-one-sheet-275-x-41-/a/7109-87430.s?ic4=GalleryView-Thumbnail-071515\">Heritage Auctions</a>.", "source": "commons-desc-page", "hidden": ""}, "Artist": {"value": "\"\u00a9 1939 by <a href=\"https://en.wikipedia.org/wiki/United_Artists\" class=\"extiw\" title=\"w:United Artists\">United Artists Corporation</a>.\"", "source": "commons-desc-page"}, "Permission": {"value": "The poster included a valid copyright notice, seen at bottom left. However, the copyright for the artwork was not renewed, as was required by American copyright law to extend/maintain protection for works published 1963 or earlier. In order to maintain copyright protection, the poster would have had to be renewed 28 years after publication, in either <a rel=\"nofollow\" class=\"external text\" href=\"https://onlinebooks.library.upenn.edu/cce/1966r.html\">1966</a> or <a rel=\"nofollow\" class=\"external text\" href=\"https://onlinebooks.library.upenn.edu/cce/1967r.html\">1967</a> (see the sections for \"Artwork: Original registrations and renewals\" and refer to the links to search the copyright catalogs for those years). Because it was not renewed, copyright lapsed at that time. Note that the poster art is a distinct work from the film it represents and had to be renewed separately.", "source": "commons-desc-page", "hidden": ""}, "LicenseShortName": {"value": "Public domain", "source": "commons-desc-page", "hidden": ""}, "UsageTerms": {"value": "Public domain", "source": "commons-desc-page", "hidden": ""}, "AttributionRequired": {"value": "false", "source": "commons-desc-page", "hidden": ""}, "Copyrighted": {"value": "False", "source": "commons-desc-page", "hidden": ""}, "Restrictions": {"value": "", "source": "commons-desc-page", "hidden": ""}, "License": {"value": "pd", "source": "commons-templates", "hidden": ""}}}, {"file": "File:Rebecca (1939 poster).jpeg", "kind": "wikidata-image", "orig": "Rebecca (1939 poster).jpeg", "timestamp": "2020-01-08T01:41:59Z", "size": 1322494, "width": 2013, "height": 3000, "url": "https://upload.wikimedia.org/wikipedia/commons/a/ad/Rebecca_%281939_poster%29.jpeg", "descriptionurl": "https://commons.wikimedia.org/wiki/File:Rebecca_(1939_poster).jpeg", "descriptionshorturl": "https://commons.wikimedia.org/w/index.php?curid=85711698", "title": "File:Rebecca (1939 poster).jpeg", "metadata": {"DateTime": {"value": "2020-01-08 01:41:59", "source": "mediawiki-metadata", "hidden": ""}, "ObjectName": {"value": "Rebecca (1939 poster)", "source": "mediawiki-metadata", "hidden": ""}, "CommonsMetadataExtension": {"value": 1.2, "source": "extension", "hidden": ""}, "Categories": {"value": "Film posters of the United States, 1940|PD-Art (PD-US-not renewed)|PD US not renewed|Rebecca (film)", "source": "commons-categories", "hidden": ""}, "Assessments": {"value": "", "source": "commons-categories", "hidden": ""}, "ImageDescription": {"value": "Theatrical poster for the American release of <a href=\"https://en.wikipedia.org/wiki/Alfred_Hitchcock\" class=\"extiw\" title=\"w:Alfred Hitchcock\">Alfred Hitchcock</a>'s 1940 film <i><a href=\"https://en.wikipedia.org/wiki/Rebecca_(1940_film)\" class=\"extiw\" title=\"w:Rebecca (1940 film)\">Rebecca</a></i>.", "source": "commons-desc-page"}, "DateTimeOriginal": {"value": "1939, per the copyright notice. Note that the film itself premiered March 1940. The poster was likely published in late 1939 to promote the film's coming release.", "source": "commons-desc-page"}, "Credit": {"value": "Scan via <a rel=\"nofollow\" class=\"external text\" href=\"https://movieposters.ha.com/itm/hitchcock/rebecca-united-artists-1940-one-sheet-275-x-41-/a/7109-87430.s?ic4=GalleryView-Thumbnail-071515\">Heritage Auctions</a>.", "source": "commons-desc-page", "hidden": ""}, "Artist": {"value": "\"\u00a9 1939 by <a href=\"https://en.wikipedia.org/wiki/United_Artists\" class=\"extiw\" title=\"w:United Artists\">United Artists Corporation</a>.\"", "source": "commons-desc-page"}, "Permission": {"value": "The poster included a valid copyright notice, seen at bottom left. However, the copyright for the artwork was not renewed, as was required by American copyright law to extend/maintain protection for works published 1963 or earlier. In order to maintain copyright protection, the poster would have had to be renewed 28 years after publication, in either <a rel=\"nofollow\" class=\"external text\" href=\"https://onlinebooks.library.upenn.edu/cce/1966r.html\">1966</a> or <a rel=\"nofollow\" class=\"external text\" href=\"https://onlinebooks.library.upenn.edu/cce/1967r.html\">1967</a> (see the sections for \"Artwork: Original registrations and renewals\" and refer to the links to search the copyright catalogs for those years). Because it was not renewed, copyright lapsed at that time. Note that the poster art is a distinct work from the film it represents and had to be renewed separately.", "source": "commons-desc-page", "hidden": ""}, "LicenseShortName": {"value": "Public domain", "source": "commons-desc-page", "hidden": ""}, "UsageTerms": {"value": "Public domain", "source": "commons-desc-page", "hidden": ""}, "AttributionRequired": {"value": "false", "source": "commons-desc-page", "hidden": ""}, "Copyrighted": {"value": "False", "source": "commons-desc-page", "hidden": ""}, "Restrictions": {"value": "", "source": "commons-desc-page", "hidden": ""}, "License": {"value": "pd", "source": "commons-templates", "hidden": ""}}}, {"kind": "restbase-original", "width": 2013, "height": 3000, "url": "https://upload.wikimedia.org/wikipedia/commons/a/ad/Rebecca_%281939_poster%29.jpeg", "file": "File:Rebecca %281939 poster%29.jpeg", "orig": "Rebecca_%281939_poster%29.jpeg"}, {"kind": "restbase-thumb", "width": 215, "height": 320, "url": "https://upload.wikimedia.org/wikipedia/commons/thumb/a/ad/Rebecca_%281939_poster%29.jpeg/215px-Rebecca_%281939_poster%29.jpeg", "file": "File:215px-Rebecca %281939 poster%29.jpeg", "orig": "215px-Rebecca_%281939_poster%29.jpeg"}]}